re_add_modeler/__init__.py
re_add_modeler/re_add_modeler_gui.py
re_add_modeler/gui_files/__init__.py
re_add_modeler/gui_files/tempCodeRunnerFile.py
re_add_modeler/gui_files/wgt_df.py
re_add_modeler/gui_files/wgt_image.py
re_add_modeler/gui_files/wgt_m_table.py
re_add_modeler/gui_files/wgt_qtext_window.py
re_add_modeler/gui_files/wgt_reactions.py
re_add_modeler/gui_files/wgt_sb_string.py
re_add_modeler/gui_files/wgt_table.py
re_add_modeler/gui_files/window_data.py
re_add_modeler/gui_files/window_model.py
re_add_modeler/gui_files/window_results.py
re_add_modeler/temp/__init__.py
re_add_modeler/utils/__init__.py
re_add_modeler/utils/convert_to_df.py
re_add_modeler/utils/storage_paths.py
re_add_modeler/utils/utils.py
re_add_modeler-0.0.2.dist-info/licenses/LICENSE
re_add_modeler-0.0.2.dist-info/METADATA
re_add_modeler-0.0.2.dist-info/WHEEL
re_add_modeler-0.0.2.dist-info/top_level.txt
re_add_modeler-0.0.2.dist-info/RECORD
