Metadata-Version: 2.4
Name: re-add-modeler
Version: 0.0.2
Summary: GUI for modeling re-addition time courses.
Author: Finn
License: MIT
Classifier: Programming Language :: Python :: 3
Classifier: License :: OSI Approved :: MIT License
License-File: LICENSE
Requires-Dist: matplotlib
Requires-Dist: pyside6==6.7.1
Requires-Dist: okin
Dynamic: license-file
